nbtty/__init__.py
nbtty/core.py
nbtty-1.1.1.dist-info/LICENSE
nbtty-1.1.1.dist-info/METADATA
nbtty-1.1.1.dist-info/WHEEL
nbtty-1.1.1.dist-info/pbr.json
nbtty-1.1.1.dist-info/top_level.txt
nbtty-1.1.1.dist-info/RECORD
